psycopg/__init__.py
psycopg/_acompat.py
psycopg/_adapters_map.py
psycopg/_capabilities.py
psycopg/_cmodule.py
psycopg/_column.py
psycopg/_compat.py
psycopg/_connection_base.py
psycopg/_connection_info.py
psycopg/_conninfo_attempts.py
psycopg/_conninfo_attempts_async.py
psycopg/_conninfo_utils.py
psycopg/_copy.py
psycopg/_copy_async.py
psycopg/_copy_base.py
psycopg/_cursor_base.py
psycopg/_dns.py
psycopg/_encodings.py
psycopg/_enums.py
psycopg/_oids.py
psycopg/_pipeline.py
psycopg/_preparing.py
psycopg/_py_transformer.py
psycopg/_queries.py
psycopg/_struct.py
psycopg/_tpc.py
psycopg/_transformer.py
psycopg/_typeinfo.py
psycopg/_typemod.py
psycopg/_tz.py
psycopg/_wrappers.py
psycopg/abc.py
psycopg/adapt.py
psycopg/client_cursor.py
psycopg/connection.py
psycopg/connection_async.py
psycopg/conninfo.py
psycopg/copy.py
psycopg/cursor.py
psycopg/cursor_async.py
psycopg/dbapi20.py
psycopg/errors.py
psycopg/generators.py
psycopg/postgres.py
psycopg/py.typed
psycopg/raw_cursor.py
psycopg/rows.py
psycopg/server_cursor.py
psycopg/sql.py
psycopg/transaction.py
psycopg/version.py
psycopg/waiting.py
psycopg/crdb/__init__.py
psycopg/crdb/_types.py
psycopg/crdb/connection.py
psycopg/pq/__init__.py
psycopg/pq/_debug.py
psycopg/pq/_enums.py
psycopg/pq/_pq_ctypes.py
psycopg/pq/_pq_ctypes.pyi
psycopg/pq/abc.py
psycopg/pq/misc.py
psycopg/pq/pq_ctypes.py
psycopg/types/__init__.py
psycopg/types/array.py
psycopg/types/bool.py
psycopg/types/composite.py
psycopg/types/datetime.py
psycopg/types/enum.py
psycopg/types/hstore.py
psycopg/types/json.py
psycopg/types/multirange.py
psycopg/types/net.py
psycopg/types/none.py
psycopg/types/numeric.py
psycopg/types/numpy.py
psycopg/types/range.py
psycopg/types/shapely.py
psycopg/types/string.py
psycopg/types/uuid.py
psycopg-3.2.3.dist-info/LICENSE.txt
psycopg-3.2.3.dist-info/METADATA
psycopg-3.2.3.dist-info/WHEEL
psycopg-3.2.3.dist-info/top_level.txt
psycopg-3.2.3.dist-info/RECORD
