Metadata-Version: 2.1
Name: psycopg
Version: 3.2.3
Summary: PostgreSQL database adapter for Python
Home-page: https://psycopg.org/psycopg3/
Author: Daniele Varrazzo
Author-email: daniele.varrazzo@gmail.com
License: GNU Lesser General Public License v3 (LGPLv3)
Project-URL: Homepage, https://psycopg.org/
Project-URL: Documentation, https://psycopg.org/psycopg3/docs/
Project-URL: Changes, https://psycopg.org/psycopg3/docs/news.html
Project-URL: Code, https://github.com/psycopg/psycopg
Project-URL: Issue Tracker, https://github.com/psycopg/psycopg/issues
Project-URL: Download, https://pypi.org/project/psycopg/
Classifier: Development Status :: 5 - Production/Stable
Classifier: Intended Audience :: Developers
Classifier: License :: OSI Approved :: GNU Lesser General Public License v3 (LGPLv3)
Classifier: Operating System :: MacOS :: MacOS X
Classifier: Operating System :: Microsoft :: Windows
Classifier: Operating System :: POSIX
Classifier: Programming Language :: Python :: 3
Classifier: Programming Language :: Python :: 3.8
Classifier: Programming Language :: Python :: 3.9
Classifier: Programming Language :: Python :: 3.10
Classifier: Programming Language :: Python :: 3.11
Classifier: Programming Language :: Python :: 3.12
Classifier: Programming Language :: Python :: 3.13
Classifier: Programming Language :: Python :: Implementation :: CPython
Classifier: Programming Language :: Python :: Implementation :: PyPy
Classifier: Topic :: Database
Classifier: Topic :: Database :: Front-Ends
Classifier: Topic :: Software Development
Classifier: Topic :: Software Development :: Libraries :: Python Modules
Requires-Python: >=3.8
License-File: LICENSE.txt
Requires-Dist: backports.zoneinfo>=0.2.0; python_version < "3.9"
Requires-Dist: typing-extensions>=4.6; python_version < "3.13"
Requires-Dist: tzdata; sys_platform == "win32"
Provides-Extra: c
Requires-Dist: psycopg-c==3.2.3; implementation_name != "pypy" and extra == "c"
Provides-Extra: binary
Requires-Dist: psycopg-binary==3.2.3; implementation_name != "pypy" and extra == "binary"
Provides-Extra: pool
Requires-Dist: psycopg-pool; extra == "pool"
Provides-Extra: test
Requires-Dist: anyio>=4.0; extra == "test"
Requires-Dist: mypy>=1.11; extra == "test"
Requires-Dist: pproxy>=2.7; extra == "test"
Requires-Dist: pytest>=6.2.5; extra == "test"
Requires-Dist: pytest-cov>=3.0; extra == "test"
Requires-Dist: pytest-randomly>=3.5; extra == "test"
Provides-Extra: dev
Requires-Dist: ast-comments>=1.1.2; extra == "dev"
Requires-Dist: black>=24.1.0; extra == "dev"
Requires-Dist: codespell>=2.2; extra == "dev"
Requires-Dist: dnspython>=2.1; extra == "dev"
Requires-Dist: flake8>=4.0; extra == "dev"
Requires-Dist: mypy>=1.11; extra == "dev"
Requires-Dist: types-setuptools>=57.4; extra == "dev"
Requires-Dist: wheel>=0.37; extra == "dev"
Provides-Extra: docs
Requires-Dist: Sphinx>=5.0; extra == "docs"
Requires-Dist: furo==2022.6.21; extra == "docs"
Requires-Dist: sphinx-autobuild>=2021.3.14; extra == "docs"
Requires-Dist: sphinx-autodoc-typehints>=1.12; extra == "docs"
